ipfcolor/__init__.py
ipfcolor/ipfcolor.py
ipfcolor/orientation.py
ipfcolor/quaternion.py
ipfcolor-0.3.dist-info/DESCRIPTION.rst
ipfcolor-0.3.dist-info/METADATA
ipfcolor-0.3.dist-info/RECORD
ipfcolor-0.3.dist-info/WHEEL
ipfcolor-0.3.dist-info/metadata.json
ipfcolor-0.3.dist-info/top_level.txt
