Metadata-Version: 2.0
Name: ipfcolor
Version: 0.3
Summary: Python implementation of DREAM3D IPF color generator
Home-page: http://github.com/kyledpierson/ipfcolor
Author: Kyle Pierson
Author-email: kyledpierson@gmail.com
License: MIT
Platform: UNKNOWN
Requires-Dist: numpy
